fail_kit_langchain.py
fail_kit-2.0.0.dist-info/METADATA
fail_kit-2.0.0.dist-info/WHEEL
fail_kit-2.0.0.dist-info/top_level.txt
fail_kit-2.0.0.dist-info/RECORD
