Metadata-Version: 2.4
Name: fail-kit
Version: 2.0.0
Summary: F.A.I.L. Kit adapter for LangChain agents - Receipts, auditing, policy enforcement, compliance, and resilience
Author: F.A.I.L. Kit Contributors
License: MIT
Project-URL: Homepage, https://github.com/resetroot99/The-FAIL-Kit
Project-URL: Documentation, https://github.com/resetroot99/The-FAIL-Kit/tree/main/middleware/langchain
Project-URL: Repository, https://github.com/resetroot99/The-FAIL-Kit
Project-URL: Issues, https://github.com/resetroot99/The-FAIL-Kit/issues
Project-URL: Changelog, https://github.com/resetroot99/The-FAIL-Kit/blob/main/CHANGELOG.md
Keywords: ai,agents,langchain,auditing,testing,receipts,llm,openai,anthropic,fail-kit,compliance,soc2,hipaa,gdpr
Classifier: Development Status :: 5 - Production/Stable
Classifier: Intended Audience :: Developers
Classifier: License :: OSI Approved :: MIT License
Classifier: Programming Language :: Python :: 3
Classifier: Programming Language :: Python :: 3.9
Classifier: Programming Language :: Python :: 3.10
Classifier: Programming Language :: Python :: 3.11
Classifier: Programming Language :: Python :: 3.12
Classifier: Programming Language :: Python :: 3.13
Classifier: Topic :: Software Development :: Testing
Classifier: Topic :: Scientific/Engineering :: Artificial Intelligence
Classifier: Topic :: Security
Requires-Python: >=3.9
Requires-Dist: langchain>=0.1.0
Requires-Dist: langchain-core>=0.1.0
Requires-Dist: pydantic>=2.0.0
Provides-Extra: fastapi
Requires-Dist: fastapi>=0.100.0; extra == "fastapi"
Requires-Dist: uvicorn>=0.23.0; extra == "fastapi"
Provides-Extra: dev
Requires-Dist: pytest>=7.0.0; extra == "dev"
Requires-Dist: pytest-asyncio>=0.21.0; extra == "dev"
Requires-Dist: httpx>=0.24.0; extra == "dev"
Requires-Dist: langchain-openai>=0.0.5; extra == "dev"
Provides-Extra: langgraph
Requires-Dist: langgraph>=0.0.20; extra == "langgraph"
Provides-Extra: all
Requires-Dist: fastapi>=0.100.0; extra == "all"
Requires-Dist: uvicorn>=0.23.0; extra == "all"
Requires-Dist: langgraph>=0.0.20; extra == "all"
